<?xml version="1.0"?>
<!DOCTYPE hibernate-mapping PUBLIC "-//Hibernate/Hibernate Mapping DTD 3.0//EN"
"http://hibernate.sourceforge.net/hibernate-mapping-3.0.dtd">
<!-- Generated 02/02/2007 08:38:17 by Hibernate Tools 3.1.0.beta5 -->
<hibernate-mapping>
    <class name="br.com.indrasistemas.vivonet.datalayer.contatoadm.Dominio" table="DOMINIO" schema="CONTATOADM">
        <id name="iddominio" type="long">
            <column name="IDDOMINIO" precision="22" scale="0" />
            <generator class="sequence">
                <param name="sequence">CONTATOADM.DOMINIOSQ</param>
            </generator>
        </id>
        <many-to-one name="tabeladominio" class="br.com.indrasistemas.vivonet.datalayer.contatoadm.Tabeladominio" fetch="select">
            <column name="IDTABELADOMINIO" precision="22" scale="0" not-null="true" />
        </many-to-one>
        <many-to-one name="tipolinha" class="br.com.indrasistemas.vivonet.datalayer.apoio.Tipolinha" fetch="select">
            <column name="IDTIPOLINHA" precision="22" scale="0" not-null="true" />
        </many-to-one>
        <many-to-one name="ufoperadora" class="br.com.indrasistemas.vivonet.datalayer.customer.Ufoperadora" fetch="select">
            <column name="IDUFOPERADORA" precision="22" scale="0" not-null="true" />
        </many-to-one>
        <property name="nmdominio" type="string">
            <column name="NMDOMINIO" />
        </property>
        <property name="indisponibilidade" type="big_decimal">
            <column name="INDISPONIBILIDADE" precision="22" scale="0" />
        </property>
        <property name="idusuarioalteracao" type="big_decimal">
            <column name="IDUSUARIOALTERACAO" precision="22" scale="0" />
        </property>
        <property name="dtultimaalteracao" type="date">
            <column name="DTULTIMAALTERACAO" length="7" />
        </property>
        <set name="atendimentofrmcampos" inverse="true">
            <key>
                <column name="IDDOMINIO" precision="22" scale="0" />
            </key>
            <one-to-many class="br.com.indrasistemas.vivonet.datalayer.atendimento.Atendimentofrmcampo" />
        </set>
    </class>
</hibernate-mapping>
