<?xml version="1.0"?>
<!DOCTYPE hibernate-mapping PUBLIC "-//Hibernate/Hibernate Mapping DTD 3.0//EN"
"http://hibernate.sourceforge.net/hibernate-mapping-3.0.dtd">
<!-- Generated 02/02/2007 08:38:17 by Hibernate Tools 3.1.0.beta5 -->
<hibernate-mapping>
    <class name="br.com.indrasistemas.vivonet.datalayer.contatoadm.Sequencia" table="SEQUENCIA" schema="CONTATOADM">
        <id name="idsequencia" type="long">
            <column name="IDSEQUENCIA" precision="22" scale="0" />
            <generator class="sequence">
                <param name="sequence">CONTATOADM.SEQUENCIASQ</param>
            </generator>
        </id>
        <many-to-one name="tiposequencia" class="br.com.indrasistemas.vivonet.datalayer.contatoadm.Tiposequencia" fetch="select">
            <column name="IDTIPOSEQUENCIA" precision="22" scale="0" not-null="true" />
        </many-to-one>
        <many-to-one name="contatogrupo" class="br.com.indrasistemas.vivonet.datalayer.contatoadm.Contatogrupo" fetch="select">
            <column name="IDCONTATOGRUPO" precision="22" scale="0" not-null="true" />
        </many-to-one>
        <property name="sqordem" type="big_decimal">
            <column name="SQORDEM" precision="22" scale="0" />
        </property>
        <property name="idusuarioalteracao" type="big_decimal">
            <column name="IDUSUARIOALTERACAO" precision="22" scale="0" />
        </property>
        <property name="dtultimaalteracao" type="date">
            <column name="DTULTIMAALTERACAO" length="7" />
        </property>
        <property name="dtexclusao" type="date">
            <column name="DTEXCLUSAO" length="7" />
        </property>
        <set name="tiporetornosequencias" inverse="true">
            <key>
                <column name="IDSEQUENCIA" precision="22" scale="0" not-null="true" />
            </key>
            <one-to-many class="br.com.indrasistemas.vivonet.datalayer.contatoadm.Tiporetornosequencia" />
        </set>
        <set name="nivelsequenciasForIdsequenciamandatoria" inverse="true">
            <key>
                <column name="IDSEQUENCIAMANDATORIA" precision="22" scale="0" not-null="true" />
            </key>
            <one-to-many class="br.com.indrasistemas.vivonet.datalayer.contatoadm.Nivelsequencia" />
        </set>
        <set name="nivelsequenciasForIdsequencia" inverse="true">
            <key>
                <column name="IDSEQUENCIA" precision="22" scale="0" not-null="true" />
            </key>
            <one-to-many class="br.com.indrasistemas.vivonet.datalayer.contatoadm.Nivelsequencia" />
        </set>
    </class>
</hibernate-mapping>
