<msg>
	<msgHdr>
		<user>1</user>
		<service>CERRAMEFEC</service>
		<sequence>16</sequence>
	</msgHdr>
	<msgBody>
		<WFExecucao>
			<ScriptExecucaoVO>
				<idAtendimento>37528</idAtendimento>
				<idTipoRetornoContato>0</idTipoRetornoContato>
				<idFase>2</idFase>
				<idAtividade>14</idAtividade>
				<idAgrupamentoEstadoTProcFut>9</idAgrupamentoEstadoTProcFut>
				<idAgrupamentoEstadoTProcAt>4</idAgrupamentoEstadoTProcAt>
				<idPessoaUsuario>1</idPessoaUsuario>
				<nmUrlDestino>1</nmUrlDestino>
			</ScriptExecucaoVO>
			<AtendimentoWorkflowVO xmlns:vo="workflow.fo.vivo.com.br/vo">
				<AtendimentoWorkflowComumVO>
					<dsObservacao>teste ã õ ñ é í</dsObservacao>
					<WFGrupoVO>
						<idGrupo/>
					</WFGrupoVO>
					<WFMotivoVO>
						<idMotivo/>
					</WFMotivoVO>
					<UsuarioVIVO xmlns:vo1="usuario.fo.vivo.com.br/vo">
						<idPessoaUsuario/>
					</UsuarioVIVO>
				</AtendimentoWorkflowComumVO>
				<AtendimentoWorkflowEncerramentoVO>
					<ArvoreEncerramentoVO xmlns:vo1="admsistemas.fo.vivo.com.br/vo">
						<EncerramentoVO>
							<idBaixa>1664</idBaixa>
							<idBaixaMensagem>527</idBaixaMensagem>
							<dsComentario>teste ã õ ñ é í</dsComentario>
							<dsDocumentoAssociado/>
						</EncerramentoVO>
					</ArvoreEncerramentoVO>
				</AtendimentoWorkflowEncerramentoVO>
			</AtendimentoWorkflowVO>
		</WFExecucao>
	</msgBody>
</msg>