<?xml version="1.0" encoding="ISO-8859-1" standalone="yes"?>
<msg>
  <msgHdr>
    <user>9999</user>
    <service>ATDABREPROT</service>
  </msgHdr>
  <msgBody>
  <!-- 
       Somente as tags idTipoAberturaProtocolo e idSistemaOrigem
       sao sempre obrigatorias e dependendo do tipo de abertura
       (idTipoAberturaProtocolo) as seguintes tags também serão
       obrigatórias:
       
				1)	Abertura por pessoa (idTipoAberturaProtocolo=4):
				a.	cdAreaRegistroSMS e nrTelefoneSMS
				
				2)	Abertura por linha de cliente (idTipoAberturaProtocolo=3):
				a.	cdAreaRegistro e nrTelefone
			
				3)	Abertura por linha de não cliente (idTipoAberturaProtocolo=2):
				a.	cdAreaRegistro e nrTelefone
				
				4)	Abertura por conta (idTipoAberturaProtocolo=1):
				a.	cdConta
				b.	cdAreaRegistroSMS e nrTelefoneSMS
		
		Ficou como concenso de todos que o melhor é enviar todos os dados 
		possíveis que o aplicativo chamador tiver em mãos. Assim sempre que
		o chamador possuir valores daquelas tags não obrigatórias é bom
		enviar para ajudar nas pesquisas de histórico futuras.
	-->
    <AbreProtocoloTO>
      <nrProtocolo>999999</nrProtocolo>
      <idTipoAberturaProtocolo>99</idTipoAberturaProtocolo>
      <cdAreaRegistro>99</cdAreaRegistro>
      <nrTelefone>999999999</nrTelefone>
      <cdAreaRegistroSMS>99</cdAreaRegistroSMS>
      <nrTelefoneSMS>999999999</nrTelefoneSMS>
      <idSistemaOrigem>99</idSistemaOrigem>
      <cdConta>XXXXXXXXXXXXXXXXX</cdConta>
    </AbreProtocoloTO>
  </msgBody>
</msg>
