<?xml version="1.0" encoding="ISO-8859-1"?>
<msg>
    <msgHdr>
        <user>RouterUser</user>
        <userID>4321</userID>
        <service>CustomService</service>
    </msgHdr>
        <xml-fragment>
            <WFRelatoriosQuebraVO xmlns:vo="workflow.fo.vivo.com.br/vo">
                <idCampo>idUfOperadora</idCampo>
                <dsCampo>Operadora</dsCampo>
            </WFRelatoriosQuebraVO>
            <WFRelatoriosQuebraVO xmlns:vo="workflow.fo.vivo.com.br/vo">
                <idCampo>nmGrupo</idCampo>
                <dsCampo>Grupo</dsCampo>
            </WFRelatoriosQuebraVO>
            <WFRelatoriosQuebraVO xmlns:vo="workflow.fo.vivo.com.br/vo">
                <idCampo>path</idCampo>
                <dsCampo>Tipo de Processo</dsCampo>
            </WFRelatoriosQuebraVO>
            <WFRelatoriosQuebraVO xmlns:vo="workflow.fo.vivo.com.br/vo">
                <idCampo>sgTipoCarteira</idCampo>
                <dsCampo>Carteira</dsCampo>
            </WFRelatoriosQuebraVO>
            <WFRelatoriosQuebraVO xmlns:vo="workflow.fo.vivo.com.br/vo">
                <idCampo>sgSegmentacao</idCampo>
                <dsCampo>Segmentação</dsCampo>
            </WFRelatoriosQuebraVO>
            <dtInicio xmlns:vo="workflow.fo.vivo.com.br/vo">01/01/2004</dtInicio>
            <dtFim xmlns:vo="workflow.fo.vivo.com.br/vo">31/12/2004</dtFim>
        </xml-fragment>
    <msgBody>
    </msgBody>
</msg>
