<?xml version="1.0" encoding="ISO-8859-1"?>
<config>
        <servers>
                <server name="srvproccad">
                        <name>srvproccad</name>
                        <logLevel>0</logLevel>
                        <logFilePath>../log/</logFilePath>
                        <logPrefix>srvproccad</logPrefix>
                        <services>
                                <service>
                                        <name>TUXPREPAGOBE</name>
                                        <type>sync</type>
                                        <tuxService>TUXPREPAGOBE</tuxService>
                                        <timeout>0</timeout>
                                        <flags>
                                                <flag>TPNOTRAN</flag>
                                        </flags> 
                                </service>
                                <service>
                                        <name>CADPP</name>
                                        <type>sync</type>
                                        <tuxService>CADPP</tuxService>
                                        <timeout>0</timeout>
                                        <flags>
                                                <flag>TPNOTRAN</flag>
                                        </flags>
                                </service>
                        </services>
                </server>
        </servers>
</config>
